LICENSE
README.md
setup.py
regru_cloudapi/__init__.py
regru_cloudapi/utils.py
regru_cloudapi.egg-info/PKG-INFO
regru_cloudapi.egg-info/SOURCES.txt
regru_cloudapi.egg-info/dependency_links.txt
regru_cloudapi.egg-info/requires.txt
regru_cloudapi.egg-info/top_level.txt