Metadata-Version: 2.1
Name: regru-cloudapi
Version: 1.2.13
Summary: Reg.ru CloudAPI Python library
Home-page: https://github.com/plvskiy/regru_cloudapi
Author: Matthew Polovskiy
Author-email: github@plvskiy.ru
License: MIT
Classifier: Programming Language :: Python :: 3
Classifier: License :: OSI Approved :: MIT License
Requires-Python: >=3.6
License-File: LICENSE
